MANIFEST.in
README
README.rst
setup.cfg
setup.py
Flask_Dashed.egg-info/PKG-INFO
Flask_Dashed.egg-info/SOURCES.txt
Flask_Dashed.egg-info/dependency_links.txt
Flask_Dashed.egg-info/not-zip-safe
Flask_Dashed.egg-info/requires.txt
Flask_Dashed.egg-info/top_level.txt
docs/Makefile
docs/api.rst
docs/conf.py
docs/index.rst
docs/make.bat
docs/_static/favicon.ico
docs/_static/screen-edit.png
docs/_static/screen.png
docs/_themes/.git
docs/_themes/.gitignore
docs/_themes/LICENSE
docs/_themes/README
docs/_themes/flask_theme_support.py
docs/_themes/flask/layout.html
docs/_themes/flask/relations.html
docs/_themes/flask/theme.conf
docs/_themes/flask/static/flasky.css_t
docs/_themes/flask/static/small_flask.css
docs/_themes/flask_small/layout.html
docs/_themes/flask_small/theme.conf
docs/_themes/flask_small/static/flasky.css_t
docs/build/doctrees/api.doctree
docs/build/doctrees/environment.pickle
docs/build/doctrees/index.doctree
flask_dashed/__init__.py
flask_dashed/__init__.pyc
flask_dashed/admin.py
flask_dashed/admin.pyc
flask_dashed/dashboard.py
flask_dashed/dashboard.pyc
flask_dashed/views.py
flask_dashed/views.pyc
flask_dashed/ext/__init__.py
flask_dashed/ext/__init__.pyc
flask_dashed/ext/sqlalchemy.py
flask_dashed/ext/sqlalchemy.pyc
flask_dashed/static/css/normalize.css
flask_dashed/static/css/style.css
flask_dashed/static/css/style.styl
flask_dashed/static/css/vendor/nib/.git
flask_dashed/static/css/vendor/nib/.gitignore
flask_dashed/static/css/vendor/nib/.gitmodules
flask_dashed/static/css/vendor/nib/.npmignore
flask_dashed/static/css/vendor/nib/History.md
flask_dashed/static/css/vendor/nib/Makefile
flask_dashed/static/css/vendor/nib/Readme.md
flask_dashed/static/css/vendor/nib/index.styl
flask_dashed/static/css/vendor/nib/package.json
flask_dashed/static/css/vendor/nib/iconic/demo.html
flask_dashed/static/css/vendor/nib/iconic/iconic.css
flask_dashed/static/css/vendor/nib/iconic/iconic_stroke.eot
flask_dashed/static/css/vendor/nib/iconic/iconic_stroke.otf
flask_dashed/static/css/vendor/nib/iconic/iconic_stroke.svg
flask_dashed/static/css/vendor/nib/iconic/iconic_stroke.ttf
flask_dashed/static/css/vendor/nib/lib/nib.js
flask_dashed/static/css/vendor/nib/lib/nib/border.styl
